{"Category":{"0":"pastel","1":"pastel","2":"pastel","3":"pastel","4":"pastel","5":"pastel","6":"pastel","7":"pastel","8":"pastel","9":"pastel","10":"pastel","11":"pastel","12":"pastel","13":"pastel","14":"pastel","15":"pastel","16":"pastel","17":"pastel","18":"pastel","19":"pastel"},"Channel":{"0":"Pastel Flurry","1":"Pastel Flurry","2":"Pastel Flurry","3":"Pastel Flurry","4":"Pastel Flurry","5":"Pastel Flurry","6":"Pastel Flurry","7":"Pastel Flurry","8":"Pastel Flurry","9":"Pastel Flurry","10":"Pastel Flurry","11":"Pastel Flurry","12":"Pastel Flurry","13":"Pastel Flurry","14":"Pastel Flurry","15":"Pastel Flurry","16":"Pastel Flurry","17":"Pastel Flurry","18":"Pastel Flurry","19":"Pastel Flurry"},"Ch_URL":{"0":{"0":"https:\/\/www.youtube.com\/c\/WildPastelHair","1":"https:\/\/www.youtube.com\/c\/AlessandraSantosPastel","2":"https:\/\/www.youtube.com\/channel\/UCSF6vx__8xdAnUIA_fcmB2Q","3":"https:\/\/www.youtube.com\/channel\/UCIjMZ-yxmkQNw1UgfpvEGlw","4":"https:\/\/www.youtube.com\/channel\/UCENUZbRr1cWOJEn2snygrfg","5":"https:\/\/www.youtube.com\/channel\/UCTLvXWIDDkEmX1MhSZPi1MQ","6":"https:\/\/www.youtube.com\/channel\/UCZVeE4pxO9AqvGh74KYg2ig","7":"https:\/\/www.youtube.com\/channel\/UC8zl8cNK71tTS6HAdHZynZQ","8":"https:\/\/www.youtube.com\/c\/PrettyPastelPlease","9":"https:\/\/www.youtube.com\/channel\/UCH3y9O7pO-YYfU4bbcG45IA","10":"https:\/\/www.youtube.com\/channel\/UCWbq9_8fq3FqideQ3kQ47hw","11":"https:\/\/www.youtube.com\/channel\/UC88YYy0Bsk9VrVRKhklnNBg","12":"https:\/\/www.youtube.com\/channel\/UCvU3Lrgb4cPOsC3iyqEVu-Q","13":"https:\/\/www.youtube.com\/channel\/UCDaIWaaiOOmTWC9XEEigLtA","14":"https:\/\/www.youtube.com\/c\/pastel_imAhottie","15":"https:\/\/www.youtube.com\/channel\/UCNaqXQLhcLUjfc9eSxh0DPw","16":"https:\/\/www.youtube.com\/c\/PastelPlotterSonoriza%C3%A7%C3%A3oeFilmagem","17":"https:\/\/www.youtube.com\/channel\/UCFnUyWqZ2kJ3MoaxXgQt5Cw","18":"https:\/\/www.youtube.com\/channel\/UCgbHSW3RTCHYDZ6mJweu1XA","19":"https:\/\/www.youtube.com\/c\/HelloPastelBlossomTV"},"1":{"0":"https:\/\/www.youtube.com\/c\/WildPastelHair","1":"https:\/\/www.youtube.com\/c\/AlessandraSantosPastel","2":"https:\/\/www.youtube.com\/channel\/UCSF6vx__8xdAnUIA_fcmB2Q","3":"https:\/\/www.youtube.com\/channel\/UCIjMZ-yxmkQNw1UgfpvEGlw","4":"https:\/\/www.youtube.com\/channel\/UCENUZbRr1cWOJEn2snygrfg","5":"https:\/\/www.youtube.com\/channel\/UCTLvXWIDDkEmX1MhSZPi1MQ","6":"https:\/\/www.youtube.com\/channel\/UCZVeE4pxO9AqvGh74KYg2ig","7":"https:\/\/www.youtube.com\/channel\/UC8zl8cNK71tTS6HAdHZynZQ","8":"https:\/\/www.youtube.com\/c\/PrettyPastelPlease","9":"https:\/\/www.youtube.com\/channel\/UCH3y9O7pO-YYfU4bbcG45IA","10":"https:\/\/www.youtube.com\/channel\/UCWbq9_8fq3FqideQ3kQ47hw","11":"https:\/\/www.youtube.com\/channel\/UC88YYy0Bsk9VrVRKhklnNBg","12":"https:\/\/www.youtube.com\/channel\/UCvU3Lrgb4cPOsC3iyqEVu-Q","13":"https:\/\/www.youtube.com\/channel\/UCDaIWaaiOOmTWC9XEEigLtA","14":"https:\/\/www.youtube.com\/c\/pastel_imAhottie","15":"https:\/\/www.youtube.com\/channel\/UCNaqXQLhcLUjfc9eSxh0DPw","16":"https:\/\/www.youtube.com\/c\/PastelPlotterSonoriza%C3%A7%C3%A3oeFilmagem","17":"https:\/\/www.youtube.com\/channel\/UCFnUyWqZ2kJ3MoaxXgQt5Cw","18":"https:\/\/www.youtube.com\/channel\/UCgbHSW3RTCHYDZ6mJweu1XA","19":"https:\/\/www.youtube.com\/c\/HelloPastelBlossomTV"},"2":{"0":"https:\/\/www.youtube.com\/c\/WildPastelHair","1":"https:\/\/www.youtube.com\/c\/AlessandraSantosPastel","2":"https:\/\/www.youtube.com\/channel\/UCSF6vx__8xdAnUIA_fcmB2Q","3":"https:\/\/www.youtube.com\/channel\/UCIjMZ-yxmkQNw1UgfpvEGlw","4":"https:\/\/www.youtube.com\/channel\/UCENUZbRr1cWOJEn2snygrfg","5":"https:\/\/www.youtube.com\/channel\/UCTLvXWIDDkEmX1MhSZPi1MQ","6":"https:\/\/www.youtube.com\/channel\/UCZVeE4pxO9AqvGh74KYg2ig","7":"https:\/\/www.youtube.com\/channel\/UC8zl8cNK71tTS6HAdHZynZQ","8":"https:\/\/www.youtube.com\/c\/PrettyPastelPlease","9":"https:\/\/www.youtube.com\/channel\/UCH3y9O7pO-YYfU4bbcG45IA","10":"https:\/\/www.youtube.com\/channel\/UCWbq9_8fq3FqideQ3kQ47hw","11":"https:\/\/www.youtube.com\/channel\/UC88YYy0Bsk9VrVRKhklnNBg","12":"https:\/\/www.youtube.com\/channel\/UCvU3Lrgb4cPOsC3iyqEVu-Q","13":"https:\/\/www.youtube.com\/channel\/UCDaIWaaiOOmTWC9XEEigLtA","14":"https:\/\/www.youtube.com\/c\/pastel_imAhottie","15":"https:\/\/www.youtube.com\/channel\/UCNaqXQLhcLUjfc9eSxh0DPw","16":"https:\/\/www.youtube.com\/c\/PastelPlotterSonoriza%C3%A7%C3%A3oeFilmagem","17":"https:\/\/www.youtube.com\/channel\/UCFnUyWqZ2kJ3MoaxXgQt5Cw","18":"https:\/\/www.youtube.com\/channel\/UCgbHSW3RTCHYDZ6mJweu1XA","19":"https:\/\/www.youtube.com\/c\/HelloPastelBlossomTV"},"3":{"0":"https:\/\/www.youtube.com\/c\/WildPastelHair","1":"https:\/\/www.youtube.com\/c\/AlessandraSantosPastel","2":"https:\/\/www.youtube.com\/channel\/UCSF6vx__8xdAnUIA_fcmB2Q","3":"https:\/\/www.youtube.com\/channel\/UCIjMZ-yxmkQNw1UgfpvEGlw","4":"https:\/\/www.youtube.com\/channel\/UCENUZbRr1cWOJEn2snygrfg","5":"https:\/\/www.youtube.com\/channel\/UCTLvXWIDDkEmX1MhSZPi1MQ","6":"https:\/\/www.youtube.com\/channel\/UCZVeE4pxO9AqvGh74KYg2ig","7":"https:\/\/www.youtube.com\/channel\/UC8zl8cNK71tTS6HAdHZynZQ","8":"https:\/\/www.youtube.com\/c\/PrettyPastelPlease","9":"https:\/\/www.youtube.com\/channel\/UCH3y9O7pO-YYfU4bbcG45IA","10":"https:\/\/www.youtube.com\/channel\/UCWbq9_8fq3FqideQ3kQ47hw","11":"https:\/\/www.youtube.com\/channel\/UC88YYy0Bsk9VrVRKhklnNBg","12":"https:\/\/www.youtube.com\/channel\/UCvU3Lrgb4cPOsC3iyqEVu-Q","13":"https:\/\/www.youtube.com\/channel\/UCDaIWaaiOOmTWC9XEEigLtA","14":"https:\/\/www.youtube.com\/c\/pastel_imAhottie","15":"https:\/\/www.youtube.com\/channel\/UCNaqXQLhcLUjfc9eSxh0DPw","16":"https:\/\/www.youtube.com\/c\/PastelPlotterSonoriza%C3%A7%C3%A3oeFilmagem","17":"https:\/\/www.youtube.com\/channel\/UCFnUyWqZ2kJ3MoaxXgQt5Cw","18":"https:\/\/www.youtube.com\/channel\/UCgbHSW3RTCHYDZ6mJweu1XA","19":"https:\/\/www.youtube.com\/c\/HelloPastelBlossomTV"},"4":{"0":"https:\/\/www.youtube.com\/c\/WildPastelHair","1":"https:\/\/www.youtube.com\/c\/AlessandraSantosPastel","2":"https:\/\/www.youtube.com\/channel\/UCSF6vx__8xdAnUIA_fcmB2Q","3":"https:\/\/www.youtube.com\/channel\/UCIjMZ-yxmkQNw1UgfpvEGlw","4":"https:\/\/www.youtube.com\/channel\/UCENUZbRr1cWOJEn2snygrfg","5":"https:\/\/www.youtube.com\/channel\/UCTLvXWIDDkEmX1MhSZPi1MQ","6":"https:\/\/www.youtube.com\/channel\/UCZVeE4pxO9AqvGh74KYg2ig","7":"https:\/\/www.youtube.com\/channel\/UC8zl8cNK71tTS6HAdHZynZQ","8":"https:\/\/www.youtube.com\/c\/PrettyPastelPlease","9":"https:\/\/www.youtube.com\/channel\/UCH3y9O7pO-YYfU4bbcG45IA","10":"https:\/\/www.youtube.com\/channel\/UCWbq9_8fq3FqideQ3kQ47hw","11":"https:\/\/www.youtube.com\/channel\/UC88YYy0Bsk9VrVRKhklnNBg","12":"https:\/\/www.youtube.com\/channel\/UCvU3Lrgb4cPOsC3iyqEVu-Q","13":"https:\/\/www.youtube.com\/channel\/UCDaIWaaiOOmTWC9XEEigLtA","14":"https:\/\/www.youtube.com\/c\/pastel_imAhottie","15":"https:\/\/www.youtube.com\/channel\/UCNaqXQLhcLUjfc9eSxh0DPw","16":"https:\/\/www.youtube.com\/c\/PastelPlotterSonoriza%C3%A7%C3%A3oeFilmagem","17":"https:\/\/www.youtube.com\/channel\/UCFnUyWqZ2kJ3MoaxXgQt5Cw","18":"https:\/\/www.youtube.com\/channel\/UCgbHSW3RTCHYDZ6mJweu1XA","19":"https:\/\/www.youtube.com\/c\/HelloPastelBlossomTV"},"5":{"0":"https:\/\/www.youtube.com\/c\/WildPastelHair","1":"https:\/\/www.youtube.com\/c\/AlessandraSantosPastel","2":"https:\/\/www.youtube.com\/channel\/UCSF6vx__8xdAnUIA_fcmB2Q","3":"https:\/\/www.youtube.com\/channel\/UCIjMZ-yxmkQNw1UgfpvEGlw","4":"https:\/\/www.youtube.com\/channel\/UCENUZbRr1cWOJEn2snygrfg","5":"https:\/\/www.youtube.com\/channel\/UCTLvXWIDDkEmX1MhSZPi1MQ","6":"https:\/\/www.youtube.com\/channel\/UCZVeE4pxO9AqvGh74KYg2ig","7":"https:\/\/www.youtube.com\/channel\/UC8zl8cNK71tTS6HAdHZynZQ","8":"https:\/\/www.youtube.com\/c\/PrettyPastelPlease","9":"https:\/\/www.youtube.com\/channel\/UCH3y9O7pO-YYfU4bbcG45IA","10":"https:\/\/www.youtube.com\/channel\/UCWbq9_8fq3FqideQ3kQ47hw","11":"https:\/\/www.youtube.com\/channel\/UC88YYy0Bsk9VrVRKhklnNBg","12":"https:\/\/www.youtube.com\/channel\/UCvU3Lrgb4cPOsC3iyqEVu-Q","13":"https:\/\/www.youtube.com\/channel\/UCDaIWaaiOOmTWC9XEEigLtA","14":"https:\/\/www.youtube.com\/c\/pastel_imAhottie","15":"https:\/\/www.youtube.com\/channel\/UCNaqXQLhcLUjfc9eSxh0DPw","16":"https:\/\/www.youtube.com\/c\/PastelPlotterSonoriza%C3%A7%C3%A3oeFilmagem","17":"https:\/\/www.youtube.com\/channel\/UCFnUyWqZ2kJ3MoaxXgQt5Cw","18":"https:\/\/www.youtube.com\/channel\/UCgbHSW3RTCHYDZ6mJweu1XA","19":"https:\/\/www.youtube.com\/c\/HelloPastelBlossomTV"},"6":{"0":"https:\/\/www.youtube.com\/c\/WildPastelHair","1":"https:\/\/www.youtube.com\/c\/AlessandraSantosPastel","2":"https:\/\/www.youtube.com\/channel\/UCSF6vx__8xdAnUIA_fcmB2Q","3":"https:\/\/www.youtube.com\/channel\/UCIjMZ-yxmkQNw1UgfpvEGlw","4":"https:\/\/www.youtube.com\/channel\/UCENUZbRr1cWOJEn2snygrfg","5":"https:\/\/www.youtube.com\/channel\/UCTLvXWIDDkEmX1MhSZPi1MQ","6":"https:\/\/www.youtube.com\/channel\/UCZVeE4pxO9AqvGh74KYg2ig","7":"https:\/\/www.youtube.com\/channel\/UC8zl8cNK71tTS6HAdHZynZQ","8":"https:\/\/www.youtube.com\/c\/PrettyPastelPlease","9":"https:\/\/www.youtube.com\/channel\/UCH3y9O7pO-YYfU4bbcG45IA","10":"https:\/\/www.youtube.com\/channel\/UCWbq9_8fq3FqideQ3kQ47hw","11":"https:\/\/www.youtube.com\/channel\/UC88YYy0Bsk9VrVRKhklnNBg","12":"https:\/\/www.youtube.com\/channel\/UCvU3Lrgb4cPOsC3iyqEVu-Q","13":"https:\/\/www.youtube.com\/channel\/UCDaIWaaiOOmTWC9XEEigLtA","14":"https:\/\/www.youtube.com\/c\/pastel_imAhottie","15":"https:\/\/www.youtube.com\/channel\/UCNaqXQLhcLUjfc9eSxh0DPw","16":"https:\/\/www.youtube.com\/c\/PastelPlotterSonoriza%C3%A7%C3%A3oeFilmagem","17":"https:\/\/www.youtube.com\/channel\/UCFnUyWqZ2kJ3MoaxXgQt5Cw","18":"https:\/\/www.youtube.com\/channel\/UCgbHSW3RTCHYDZ6mJweu1XA","19":"https:\/\/www.youtube.com\/c\/HelloPastelBlossomTV"},"7":{"0":"https:\/\/www.youtube.com\/c\/WildPastelHair","1":"https:\/\/www.youtube.com\/c\/AlessandraSantosPastel","2":"https:\/\/www.youtube.com\/channel\/UCSF6vx__8xdAnUIA_fcmB2Q","3":"https:\/\/www.youtube.com\/channel\/UCIjMZ-yxmkQNw1UgfpvEGlw","4":"https:\/\/www.youtube.com\/channel\/UCENUZbRr1cWOJEn2snygrfg","5":"https:\/\/www.youtube.com\/channel\/UCTLvXWIDDkEmX1MhSZPi1MQ","6":"https:\/\/www.youtube.com\/channel\/UCZVeE4pxO9AqvGh74KYg2ig","7":"https:\/\/www.youtube.com\/channel\/UC8zl8cNK71tTS6HAdHZynZQ","8":"https:\/\/www.youtube.com\/c\/PrettyPastelPlease","9":"https:\/\/www.youtube.com\/channel\/UCH3y9O7pO-YYfU4bbcG45IA","10":"https:\/\/www.youtube.com\/channel\/UCWbq9_8fq3FqideQ3kQ47hw","11":"https:\/\/www.youtube.com\/channel\/UC88YYy0Bsk9VrVRKhklnNBg","12":"https:\/\/www.youtube.com\/channel\/UCvU3Lrgb4cPOsC3iyqEVu-Q","13":"https:\/\/www.youtube.com\/channel\/UCDaIWaaiOOmTWC9XEEigLtA","14":"https:\/\/www.youtube.com\/c\/pastel_imAhottie","15":"https:\/\/www.youtube.com\/channel\/UCNaqXQLhcLUjfc9eSxh0DPw","16":"https:\/\/www.youtube.com\/c\/PastelPlotterSonoriza%C3%A7%C3%A3oeFilmagem","17":"https:\/\/www.youtube.com\/channel\/UCFnUyWqZ2kJ3MoaxXgQt5Cw","18":"https:\/\/www.youtube.com\/channel\/UCgbHSW3RTCHYDZ6mJweu1XA","19":"https:\/\/www.youtube.com\/c\/HelloPastelBlossomTV"},"8":{"0":"https:\/\/www.youtube.com\/c\/WildPastelHair","1":"https:\/\/www.youtube.com\/c\/AlessandraSantosPastel","2":"https:\/\/www.youtube.com\/channel\/UCSF6vx__8xdAnUIA_fcmB2Q","3":"https:\/\/www.youtube.com\/channel\/UCIjMZ-yxmkQNw1UgfpvEGlw","4":"https:\/\/www.youtube.com\/channel\/UCENUZbRr1cWOJEn2snygrfg","5":"https:\/\/www.youtube.com\/channel\/UCTLvXWIDDkEmX1MhSZPi1MQ","6":"https:\/\/www.youtube.com\/channel\/UCZVeE4pxO9AqvGh74KYg2ig","7":"https:\/\/www.youtube.com\/channel\/UC8zl8cNK71tTS6HAdHZynZQ","8":"https:\/\/www.youtube.com\/c\/PrettyPastelPlease","9":"https:\/\/www.youtube.com\/channel\/UCH3y9O7pO-YYfU4bbcG45IA","10":"https:\/\/www.youtube.com\/channel\/UCWbq9_8fq3FqideQ3kQ47hw","11":"https:\/\/www.youtube.com\/channel\/UC88YYy0Bsk9VrVRKhklnNBg","12":"https:\/\/www.youtube.com\/channel\/UCvU3Lrgb4cPOsC3iyqEVu-Q","13":"https:\/\/www.youtube.com\/channel\/UCDaIWaaiOOmTWC9XEEigLtA","14":"https:\/\/www.youtube.com\/c\/pastel_imAhottie","15":"https:\/\/www.youtube.com\/channel\/UCNaqXQLhcLUjfc9eSxh0DPw","16":"https:\/\/www.youtube.com\/c\/PastelPlotterSonoriza%C3%A7%C3%A3oeFilmagem","17":"https:\/\/www.youtube.com\/channel\/UCFnUyWqZ2kJ3MoaxXgQt5Cw","18":"https:\/\/www.youtube.com\/channel\/UCgbHSW3RTCHYDZ6mJweu1XA","19":"https:\/\/www.youtube.com\/c\/HelloPastelBlossomTV"},"9":{"0":"https:\/\/www.youtube.com\/c\/WildPastelHair","1":"https:\/\/www.youtube.com\/c\/AlessandraSantosPastel","2":"https:\/\/www.youtube.com\/channel\/UCSF6vx__8xdAnUIA_fcmB2Q","3":"https:\/\/www.youtube.com\/channel\/UCIjMZ-yxmkQNw1UgfpvEGlw","4":"https:\/\/www.youtube.com\/channel\/UCENUZbRr1cWOJEn2snygrfg","5":"https:\/\/www.youtube.com\/channel\/UCTLvXWIDDkEmX1MhSZPi1MQ","6":"https:\/\/www.youtube.com\/channel\/UCZVeE4pxO9AqvGh74KYg2ig","7":"https:\/\/www.youtube.com\/channel\/UC8zl8cNK71tTS6HAdHZynZQ","8":"https:\/\/www.youtube.com\/c\/PrettyPastelPlease","9":"https:\/\/www.youtube.com\/channel\/UCH3y9O7pO-YYfU4bbcG45IA","10":"https:\/\/www.youtube.com\/channel\/UCWbq9_8fq3FqideQ3kQ47hw","11":"https:\/\/www.youtube.com\/channel\/UC88YYy0Bsk9VrVRKhklnNBg","12":"https:\/\/www.youtube.com\/channel\/UCvU3Lrgb4cPOsC3iyqEVu-Q","13":"https:\/\/www.youtube.com\/channel\/UCDaIWaaiOOmTWC9XEEigLtA","14":"https:\/\/www.youtube.com\/c\/pastel_imAhottie","15":"https:\/\/www.youtube.com\/channel\/UCNaqXQLhcLUjfc9eSxh0DPw","16":"https:\/\/www.youtube.com\/c\/PastelPlotterSonoriza%C3%A7%C3%A3oeFilmagem","17":"https:\/\/www.youtube.com\/channel\/UCFnUyWqZ2kJ3MoaxXgQt5Cw","18":"https:\/\/www.youtube.com\/channel\/UCgbHSW3RTCHYDZ6mJweu1XA","19":"https:\/\/www.youtube.com\/c\/HelloPastelBlossomTV"},"10":{"0":"https:\/\/www.youtube.com\/c\/WildPastelHair","1":"https:\/\/www.youtube.com\/c\/AlessandraSantosPastel","2":"https:\/\/www.youtube.com\/channel\/UCSF6vx__8xdAnUIA_fcmB2Q","3":"https:\/\/www.youtube.com\/channel\/UCIjMZ-yxmkQNw1UgfpvEGlw","4":"https:\/\/www.youtube.com\/channel\/UCENUZbRr1cWOJEn2snygrfg","5":"https:\/\/www.youtube.com\/channel\/UCTLvXWIDDkEmX1MhSZPi1MQ","6":"https:\/\/www.youtube.com\/channel\/UCZVeE4pxO9AqvGh74KYg2ig","7":"https:\/\/www.youtube.com\/channel\/UC8zl8cNK71tTS6HAdHZynZQ","8":"https:\/\/www.youtube.com\/c\/PrettyPastelPlease","9":"https:\/\/www.youtube.com\/channel\/UCH3y9O7pO-YYfU4bbcG45IA","10":"https:\/\/www.youtube.com\/channel\/UCWbq9_8fq3FqideQ3kQ47hw","11":"https:\/\/www.youtube.com\/channel\/UC88YYy0Bsk9VrVRKhklnNBg","12":"https:\/\/www.youtube.com\/channel\/UCvU3Lrgb4cPOsC3iyqEVu-Q","13":"https:\/\/www.youtube.com\/channel\/UCDaIWaaiOOmTWC9XEEigLtA","14":"https:\/\/www.youtube.com\/c\/pastel_imAhottie","15":"https:\/\/www.youtube.com\/channel\/UCNaqXQLhcLUjfc9eSxh0DPw","16":"https:\/\/www.youtube.com\/c\/PastelPlotterSonoriza%C3%A7%C3%A3oeFilmagem","17":"https:\/\/www.youtube.com\/channel\/UCFnUyWqZ2kJ3MoaxXgQt5Cw","18":"https:\/\/www.youtube.com\/channel\/UCgbHSW3RTCHYDZ6mJweu1XA","19":"https:\/\/www.youtube.com\/c\/HelloPastelBlossomTV"},"11":{"0":"https:\/\/www.youtube.com\/c\/WildPastelHair","1":"https:\/\/www.youtube.com\/c\/AlessandraSantosPastel","2":"https:\/\/www.youtube.com\/channel\/UCSF6vx__8xdAnUIA_fcmB2Q","3":"https:\/\/www.youtube.com\/channel\/UCIjMZ-yxmkQNw1UgfpvEGlw","4":"https:\/\/www.youtube.com\/channel\/UCENUZbRr1cWOJEn2snygrfg","5":"https:\/\/www.youtube.com\/channel\/UCTLvXWIDDkEmX1MhSZPi1MQ","6":"https:\/\/www.youtube.com\/channel\/UCZVeE4pxO9AqvGh74KYg2ig","7":"https:\/\/www.youtube.com\/channel\/UC8zl8cNK71tTS6HAdHZynZQ","8":"https:\/\/www.youtube.com\/c\/PrettyPastelPlease","9":"https:\/\/www.youtube.com\/channel\/UCH3y9O7pO-YYfU4bbcG45IA","10":"https:\/\/www.youtube.com\/channel\/UCWbq9_8fq3FqideQ3kQ47hw","11":"https:\/\/www.youtube.com\/channel\/UC88YYy0Bsk9VrVRKhklnNBg","12":"https:\/\/www.youtube.com\/channel\/UCvU3Lrgb4cPOsC3iyqEVu-Q","13":"https:\/\/www.youtube.com\/channel\/UCDaIWaaiOOmTWC9XEEigLtA","14":"https:\/\/www.youtube.com\/c\/pastel_imAhottie","15":"https:\/\/www.youtube.com\/channel\/UCNaqXQLhcLUjfc9eSxh0DPw","16":"https:\/\/www.youtube.com\/c\/PastelPlotterSonoriza%C3%A7%C3%A3oeFilmagem","17":"https:\/\/www.youtube.com\/channel\/UCFnUyWqZ2kJ3MoaxXgQt5Cw","18":"https:\/\/www.youtube.com\/channel\/UCgbHSW3RTCHYDZ6mJweu1XA","19":"https:\/\/www.youtube.com\/c\/HelloPastelBlossomTV"},"12":{"0":"https:\/\/www.youtube.com\/c\/WildPastelHair","1":"https:\/\/www.youtube.com\/c\/AlessandraSantosPastel","2":"https:\/\/www.youtube.com\/channel\/UCSF6vx__8xdAnUIA_fcmB2Q","3":"https:\/\/www.youtube.com\/channel\/UCIjMZ-yxmkQNw1UgfpvEGlw","4":"https:\/\/www.youtube.com\/channel\/UCENUZbRr1cWOJEn2snygrfg","5":"https:\/\/www.youtube.com\/channel\/UCTLvXWIDDkEmX1MhSZPi1MQ","6":"https:\/\/www.youtube.com\/channel\/UCZVeE4pxO9AqvGh74KYg2ig","7":"https:\/\/www.youtube.com\/channel\/UC8zl8cNK71tTS6HAdHZynZQ","8":"https:\/\/www.youtube.com\/c\/PrettyPastelPlease","9":"https:\/\/www.youtube.com\/channel\/UCH3y9O7pO-YYfU4bbcG45IA","10":"https:\/\/www.youtube.com\/channel\/UCWbq9_8fq3FqideQ3kQ47hw","11":"https:\/\/www.youtube.com\/channel\/UC88YYy0Bsk9VrVRKhklnNBg","12":"https:\/\/www.youtube.com\/channel\/UCvU3Lrgb4cPOsC3iyqEVu-Q","13":"https:\/\/www.youtube.com\/channel\/UCDaIWaaiOOmTWC9XEEigLtA","14":"https:\/\/www.youtube.com\/c\/pastel_imAhottie","15":"https:\/\/www.youtube.com\/channel\/UCNaqXQLhcLUjfc9eSxh0DPw","16":"https:\/\/www.youtube.com\/c\/PastelPlotterSonoriza%C3%A7%C3%A3oeFilmagem","17":"https:\/\/www.youtube.com\/channel\/UCFnUyWqZ2kJ3MoaxXgQt5Cw","18":"https:\/\/www.youtube.com\/channel\/UCgbHSW3RTCHYDZ6mJweu1XA","19":"https:\/\/www.youtube.com\/c\/HelloPastelBlossomTV"},"13":{"0":"https:\/\/www.youtube.com\/c\/WildPastelHair","1":"https:\/\/www.youtube.com\/c\/AlessandraSantosPastel","2":"https:\/\/www.youtube.com\/channel\/UCSF6vx__8xdAnUIA_fcmB2Q","3":"https:\/\/www.youtube.com\/channel\/UCIjMZ-yxmkQNw1UgfpvEGlw","4":"https:\/\/www.youtube.com\/channel\/UCENUZbRr1cWOJEn2snygrfg","5":"https:\/\/www.youtube.com\/channel\/UCTLvXWIDDkEmX1MhSZPi1MQ","6":"https:\/\/www.youtube.com\/channel\/UCZVeE4pxO9AqvGh74KYg2ig","7":"https:\/\/www.youtube.com\/channel\/UC8zl8cNK71tTS6HAdHZynZQ","8":"https:\/\/www.youtube.com\/c\/PrettyPastelPlease","9":"https:\/\/www.youtube.com\/channel\/UCH3y9O7pO-YYfU4bbcG45IA","10":"https:\/\/www.youtube.com\/channel\/UCWbq9_8fq3FqideQ3kQ47hw","11":"https:\/\/www.youtube.com\/channel\/UC88YYy0Bsk9VrVRKhklnNBg","12":"https:\/\/www.youtube.com\/channel\/UCvU3Lrgb4cPOsC3iyqEVu-Q","13":"https:\/\/www.youtube.com\/channel\/UCDaIWaaiOOmTWC9XEEigLtA","14":"https:\/\/www.youtube.com\/c\/pastel_imAhottie","15":"https:\/\/www.youtube.com\/channel\/UCNaqXQLhcLUjfc9eSxh0DPw","16":"https:\/\/www.youtube.com\/c\/PastelPlotterSonoriza%C3%A7%C3%A3oeFilmagem","17":"https:\/\/www.youtube.com\/channel\/UCFnUyWqZ2kJ3MoaxXgQt5Cw","18":"https:\/\/www.youtube.com\/channel\/UCgbHSW3RTCHYDZ6mJweu1XA","19":"https:\/\/www.youtube.com\/c\/HelloPastelBlossomTV"},"14":{"0":"https:\/\/www.youtube.com\/c\/WildPastelHair","1":"https:\/\/www.youtube.com\/c\/AlessandraSantosPastel","2":"https:\/\/www.youtube.com\/channel\/UCSF6vx__8xdAnUIA_fcmB2Q","3":"https:\/\/www.youtube.com\/channel\/UCIjMZ-yxmkQNw1UgfpvEGlw","4":"https:\/\/www.youtube.com\/channel\/UCENUZbRr1cWOJEn2snygrfg","5":"https:\/\/www.youtube.com\/channel\/UCTLvXWIDDkEmX1MhSZPi1MQ","6":"https:\/\/www.youtube.com\/channel\/UCZVeE4pxO9AqvGh74KYg2ig","7":"https:\/\/www.youtube.com\/channel\/UC8zl8cNK71tTS6HAdHZynZQ","8":"https:\/\/www.youtube.com\/c\/PrettyPastelPlease","9":"https:\/\/www.youtube.com\/channel\/UCH3y9O7pO-YYfU4bbcG45IA","10":"https:\/\/www.youtube.com\/channel\/UCWbq9_8fq3FqideQ3kQ47hw","11":"https:\/\/www.youtube.com\/channel\/UC88YYy0Bsk9VrVRKhklnNBg","12":"https:\/\/www.youtube.com\/channel\/UCvU3Lrgb4cPOsC3iyqEVu-Q","13":"https:\/\/www.youtube.com\/channel\/UCDaIWaaiOOmTWC9XEEigLtA","14":"https:\/\/www.youtube.com\/c\/pastel_imAhottie","15":"https:\/\/www.youtube.com\/channel\/UCNaqXQLhcLUjfc9eSxh0DPw","16":"https:\/\/www.youtube.com\/c\/PastelPlotterSonoriza%C3%A7%C3%A3oeFilmagem","17":"https:\/\/www.youtube.com\/channel\/UCFnUyWqZ2kJ3MoaxXgQt5Cw","18":"https:\/\/www.youtube.com\/channel\/UCgbHSW3RTCHYDZ6mJweu1XA","19":"https:\/\/www.youtube.com\/c\/HelloPastelBlossomTV"},"15":{"0":"https:\/\/www.youtube.com\/c\/WildPastelHair","1":"https:\/\/www.youtube.com\/c\/AlessandraSantosPastel","2":"https:\/\/www.youtube.com\/channel\/UCSF6vx__8xdAnUIA_fcmB2Q","3":"https:\/\/www.youtube.com\/channel\/UCIjMZ-yxmkQNw1UgfpvEGlw","4":"https:\/\/www.youtube.com\/channel\/UCENUZbRr1cWOJEn2snygrfg","5":"https:\/\/www.youtube.com\/channel\/UCTLvXWIDDkEmX1MhSZPi1MQ","6":"https:\/\/www.youtube.com\/channel\/UCZVeE4pxO9AqvGh74KYg2ig","7":"https:\/\/www.youtube.com\/channel\/UC8zl8cNK71tTS6HAdHZynZQ","8":"https:\/\/www.youtube.com\/c\/PrettyPastelPlease","9":"https:\/\/www.youtube.com\/channel\/UCH3y9O7pO-YYfU4bbcG45IA","10":"https:\/\/www.youtube.com\/channel\/UCWbq9_8fq3FqideQ3kQ47hw","11":"https:\/\/www.youtube.com\/channel\/UC88YYy0Bsk9VrVRKhklnNBg","12":"https:\/\/www.youtube.com\/channel\/UCvU3Lrgb4cPOsC3iyqEVu-Q","13":"https:\/\/www.youtube.com\/channel\/UCDaIWaaiOOmTWC9XEEigLtA","14":"https:\/\/www.youtube.com\/c\/pastel_imAhottie","15":"https:\/\/www.youtube.com\/channel\/UCNaqXQLhcLUjfc9eSxh0DPw","16":"https:\/\/www.youtube.com\/c\/PastelPlotterSonoriza%C3%A7%C3%A3oeFilmagem","17":"https:\/\/www.youtube.com\/channel\/UCFnUyWqZ2kJ3MoaxXgQt5Cw","18":"https:\/\/www.youtube.com\/channel\/UCgbHSW3RTCHYDZ6mJweu1XA","19":"https:\/\/www.youtube.com\/c\/HelloPastelBlossomTV"},"16":{"0":"https:\/\/www.youtube.com\/c\/WildPastelHair","1":"https:\/\/www.youtube.com\/c\/AlessandraSantosPastel","2":"https:\/\/www.youtube.com\/channel\/UCSF6vx__8xdAnUIA_fcmB2Q","3":"https:\/\/www.youtube.com\/channel\/UCIjMZ-yxmkQNw1UgfpvEGlw","4":"https:\/\/www.youtube.com\/channel\/UCENUZbRr1cWOJEn2snygrfg","5":"https:\/\/www.youtube.com\/channel\/UCTLvXWIDDkEmX1MhSZPi1MQ","6":"https:\/\/www.youtube.com\/channel\/UCZVeE4pxO9AqvGh74KYg2ig","7":"https:\/\/www.youtube.com\/channel\/UC8zl8cNK71tTS6HAdHZynZQ","8":"https:\/\/www.youtube.com\/c\/PrettyPastelPlease","9":"https:\/\/www.youtube.com\/channel\/UCH3y9O7pO-YYfU4bbcG45IA","10":"https:\/\/www.youtube.com\/channel\/UCWbq9_8fq3FqideQ3kQ47hw","11":"https:\/\/www.youtube.com\/channel\/UC88YYy0Bsk9VrVRKhklnNBg","12":"https:\/\/www.youtube.com\/channel\/UCvU3Lrgb4cPOsC3iyqEVu-Q","13":"https:\/\/www.youtube.com\/channel\/UCDaIWaaiOOmTWC9XEEigLtA","14":"https:\/\/www.youtube.com\/c\/pastel_imAhottie","15":"https:\/\/www.youtube.com\/channel\/UCNaqXQLhcLUjfc9eSxh0DPw","16":"https:\/\/www.youtube.com\/c\/PastelPlotterSonoriza%C3%A7%C3%A3oeFilmagem","17":"https:\/\/www.youtube.com\/channel\/UCFnUyWqZ2kJ3MoaxXgQt5Cw","18":"https:\/\/www.youtube.com\/channel\/UCgbHSW3RTCHYDZ6mJweu1XA","19":"https:\/\/www.youtube.com\/c\/HelloPastelBlossomTV"},"17":{"0":"https:\/\/www.youtube.com\/c\/WildPastelHair","1":"https:\/\/www.youtube.com\/c\/AlessandraSantosPastel","2":"https:\/\/www.youtube.com\/channel\/UCSF6vx__8xdAnUIA_fcmB2Q","3":"https:\/\/www.youtube.com\/channel\/UCIjMZ-yxmkQNw1UgfpvEGlw","4":"https:\/\/www.youtube.com\/channel\/UCENUZbRr1cWOJEn2snygrfg","5":"https:\/\/www.youtube.com\/channel\/UCTLvXWIDDkEmX1MhSZPi1MQ","6":"https:\/\/www.youtube.com\/channel\/UCZVeE4pxO9AqvGh74KYg2ig","7":"https:\/\/www.youtube.com\/channel\/UC8zl8cNK71tTS6HAdHZynZQ","8":"https:\/\/www.youtube.com\/c\/PrettyPastelPlease","9":"https:\/\/www.youtube.com\/channel\/UCH3y9O7pO-YYfU4bbcG45IA","10":"https:\/\/www.youtube.com\/channel\/UCWbq9_8fq3FqideQ3kQ47hw","11":"https:\/\/www.youtube.com\/channel\/UC88YYy0Bsk9VrVRKhklnNBg","12":"https:\/\/www.youtube.com\/channel\/UCvU3Lrgb4cPOsC3iyqEVu-Q","13":"https:\/\/www.youtube.com\/channel\/UCDaIWaaiOOmTWC9XEEigLtA","14":"https:\/\/www.youtube.com\/c\/pastel_imAhottie","15":"https:\/\/www.youtube.com\/channel\/UCNaqXQLhcLUjfc9eSxh0DPw","16":"https:\/\/www.youtube.com\/c\/PastelPlotterSonoriza%C3%A7%C3%A3oeFilmagem","17":"https:\/\/www.youtube.com\/channel\/UCFnUyWqZ2kJ3MoaxXgQt5Cw","18":"https:\/\/www.youtube.com\/channel\/UCgbHSW3RTCHYDZ6mJweu1XA","19":"https:\/\/www.youtube.com\/c\/HelloPastelBlossomTV"},"18":{"0":"https:\/\/www.youtube.com\/c\/WildPastelHair","1":"https:\/\/www.youtube.com\/c\/AlessandraSantosPastel","2":"https:\/\/www.youtube.com\/channel\/UCSF6vx__8xdAnUIA_fcmB2Q","3":"https:\/\/www.youtube.com\/channel\/UCIjMZ-yxmkQNw1UgfpvEGlw","4":"https:\/\/www.youtube.com\/channel\/UCENUZbRr1cWOJEn2snygrfg","5":"https:\/\/www.youtube.com\/channel\/UCTLvXWIDDkEmX1MhSZPi1MQ","6":"https:\/\/www.youtube.com\/channel\/UCZVeE4pxO9AqvGh74KYg2ig","7":"https:\/\/www.youtube.com\/channel\/UC8zl8cNK71tTS6HAdHZynZQ","8":"https:\/\/www.youtube.com\/c\/PrettyPastelPlease","9":"https:\/\/www.youtube.com\/channel\/UCH3y9O7pO-YYfU4bbcG45IA","10":"https:\/\/www.youtube.com\/channel\/UCWbq9_8fq3FqideQ3kQ47hw","11":"https:\/\/www.youtube.com\/channel\/UC88YYy0Bsk9VrVRKhklnNBg","12":"https:\/\/www.youtube.com\/channel\/UCvU3Lrgb4cPOsC3iyqEVu-Q","13":"https:\/\/www.youtube.com\/channel\/UCDaIWaaiOOmTWC9XEEigLtA","14":"https:\/\/www.youtube.com\/c\/pastel_imAhottie","15":"https:\/\/www.youtube.com\/channel\/UCNaqXQLhcLUjfc9eSxh0DPw","16":"https:\/\/www.youtube.com\/c\/PastelPlotterSonoriza%C3%A7%C3%A3oeFilmagem","17":"https:\/\/www.youtube.com\/channel\/UCFnUyWqZ2kJ3MoaxXgQt5Cw","18":"https:\/\/www.youtube.com\/channel\/UCgbHSW3RTCHYDZ6mJweu1XA","19":"https:\/\/www.youtube.com\/c\/HelloPastelBlossomTV"},"19":{"0":"https:\/\/www.youtube.com\/c\/WildPastelHair","1":"https:\/\/www.youtube.com\/c\/AlessandraSantosPastel","2":"https:\/\/www.youtube.com\/channel\/UCSF6vx__8xdAnUIA_fcmB2Q","3":"https:\/\/www.youtube.com\/channel\/UCIjMZ-yxmkQNw1UgfpvEGlw","4":"https:\/\/www.youtube.com\/channel\/UCENUZbRr1cWOJEn2snygrfg","5":"https:\/\/www.youtube.com\/channel\/UCTLvXWIDDkEmX1MhSZPi1MQ","6":"https:\/\/www.youtube.com\/channel\/UCZVeE4pxO9AqvGh74KYg2ig","7":"https:\/\/www.youtube.com\/channel\/UC8zl8cNK71tTS6HAdHZynZQ","8":"https:\/\/www.youtube.com\/c\/PrettyPastelPlease","9":"https:\/\/www.youtube.com\/channel\/UCH3y9O7pO-YYfU4bbcG45IA","10":"https:\/\/www.youtube.com\/channel\/UCWbq9_8fq3FqideQ3kQ47hw","11":"https:\/\/www.youtube.com\/channel\/UC88YYy0Bsk9VrVRKhklnNBg","12":"https:\/\/www.youtube.com\/channel\/UCvU3Lrgb4cPOsC3iyqEVu-Q","13":"https:\/\/www.youtube.com\/channel\/UCDaIWaaiOOmTWC9XEEigLtA","14":"https:\/\/www.youtube.com\/c\/pastel_imAhottie","15":"https:\/\/www.youtube.com\/channel\/UCNaqXQLhcLUjfc9eSxh0DPw","16":"https:\/\/www.youtube.com\/c\/PastelPlotterSonoriza%C3%A7%C3%A3oeFilmagem","17":"https:\/\/www.youtube.com\/channel\/UCFnUyWqZ2kJ3MoaxXgQt5Cw","18":"https:\/\/www.youtube.com\/channel\/UCgbHSW3RTCHYDZ6mJweu1XA","19":"https:\/\/www.youtube.com\/c\/HelloPastelBlossomTV"}},"Titles":{"0":"H.A.Y {AMV} (Baldi\u2019s basics Part 1)","1":"Opinions AMV (Animatic\/Animation) [Baldi\u2019s Basics Part 2] Flashing lights warning!!","2":"We\u2019ll Fly meme [PMV\/AMV] (Baldi\u2019s Basics part 3)","3":"Chandelialan Meme (Jurassic world)","4":"{Flashing Lights} TRIANGLES MEME {Flipaclip}(Gift for Dayamations) [Minecraft animation]","5":"Infinite Meme\/ AMV (Baldi's Basics) Part 4 [Finale]","6":"Animated Memes","7":"Take Control (Original meme?) [Fallen Kingdom]","8":"I'm sorry x2 meme \u3054\u3081\u3093\u306d \u3054\u3081\u3093\u306d [House Pests]","9":"RPG Meme (Flipaclip)","10":"Fallen Kingdom [Dream SMP Animation]","11":"Eyes Half Closed Meme (Jurassic World)","12":"Hanabi 2 Meme (Flipaclip)","13":"The Wolf Animation Meme (Flipaclip)","14":"Identities meme (Jurassic world) {full meme}","15":"Malto Meme (Flipaclip)","16":"Someday Meme (Flipaclip)","17":"Pretty please Animation Meme [Dream Team]","18":"Fingertips Meme \/\/Birthday Animation\/\/ (Flipaclip)","19":"\u9b3cKYOKAN PMV [MINECRAFT CHAMPIONSHIP 8]"},"Video_URL":{"0":"https:\/\/www.youtube.com\/watch?v=f_hTbwDKh8g","1":"https:\/\/www.youtube.com\/watch?v=Z7TqNzT4pcQ","2":"https:\/\/www.youtube.com\/watch?v=U8DgUSag5Sg","3":"https:\/\/www.youtube.com\/watch?v=CuTcTIUkT78","4":"https:\/\/www.youtube.com\/watch?v=hHfLbV_rWAw","5":"https:\/\/www.youtube.com\/watch?v=suCa1Vh2dFY","6":"https:\/\/www.youtube.com\/watch?v=1USLJuKvfN0","7":"https:\/\/www.youtube.com\/watch?v=RU3BDKBsniQ","8":"https:\/\/www.youtube.com\/watch?v=PLu-tqnTiJ4","9":"https:\/\/www.youtube.com\/watch?v=2qynRBA1Dlk","10":"https:\/\/www.youtube.com\/watch?v=s1K3Kqnos50","11":"https:\/\/www.youtube.com\/watch?v=qcTcqUB7cpg","12":"https:\/\/www.youtube.com\/watch?v=VkZjhtSxiD0","13":"https:\/\/www.youtube.com\/watch?v=MqX9Ku19Zlw","14":"https:\/\/www.youtube.com\/watch?v=cBmNLrZuNgQ","15":"https:\/\/www.youtube.com\/watch?v=Q3Zfc9TyDD8","16":"https:\/\/www.youtube.com\/watch?v=WadwlidS6GY","17":"https:\/\/www.youtube.com\/watch?v=UmMgTtAhFSA","18":"https:\/\/www.youtube.com\/watch?v=2cveqZKLFMA","19":"https:\/\/www.youtube.com\/watch?v=WtAA_su4zyo"},"Date":{"0":"3 years ago","1":"3 years ago","2":"2 years ago","3":"3 years ago","4":"2 years ago","5":"2 years ago","6":"2 years ago","7":"3 years ago","8":"2 years ago","9":"2 years ago","10":"1 year ago","11":"2 years ago","12":"1 year ago","13":"2 years ago","14":"3 years ago","15":"2 years ago","16":"2 years ago","17":"1 year ago","18":"2 years ago","19":"1 year ago"},"View_2022-01-12":{"0":"25M views","1":"23M views","2":"8.6M views","3":"7.2M views","4":"4.6M views","5":"2.6M views","6":"2.4M views","7":"2M views","8":"1.8M views","9":"1.5M views","10":"1.2M views","11":"1.1M views","12":"1.1M views","13":"1M views","14":"1M views","15":"869K views","16":"850K views","17":"764K views","18":"521K views","19":"505K views"},"Subs_2022-01-12":{"0":"440K subscribers","1":"440K subscribers","2":"440K subscribers","3":"440K subscribers","4":"440K subscribers","5":"440K subscribers","6":"440K subscribers","7":"440K subscribers","8":"440K subscribers","9":"440K subscribers","10":"440K subscribers","11":"440K subscribers","12":"440K subscribers","13":"440K subscribers","14":"440K subscribers","15":"440K subscribers","16":"440K subscribers","17":"440K subscribers","18":"440K subscribers","19":"440K subscribers"}}