{"Category":{"0":"pastel","1":"pastel","2":"pastel","3":"pastel","4":"pastel","5":"pastel","6":"pastel","7":"pastel","8":"pastel","9":"pastel","10":"pastel","11":"pastel","12":"pastel","13":"pastel","14":"pastel","15":"pastel","16":"pastel","17":"pastel","18":"pastel","19":"pastel"},"Channel":{"0":"Pastel Sounds","1":"Pastel Sounds","2":"Pastel Sounds","3":"Pastel Sounds","4":"Pastel Sounds","5":"Pastel Sounds","6":"Pastel Sounds","7":"Pastel Sounds","8":"Pastel Sounds","9":"Pastel Sounds","10":"Pastel Sounds","11":"Pastel Sounds","12":"Pastel Sounds","13":"Pastel Sounds","14":"Pastel Sounds","15":"Pastel Sounds","16":"Pastel Sounds","17":"Pastel Sounds","18":"Pastel Sounds","19":"Pastel Sounds"},"Ch_URL":{"0":{"0":"https:\/\/www.youtube.com\/c\/WildPastelHair","1":"https:\/\/www.youtube.com\/c\/AlessandraSantosPastel","2":"https:\/\/www.youtube.com\/channel\/UCSF6vx__8xdAnUIA_fcmB2Q","3":"https:\/\/www.youtube.com\/channel\/UCIjMZ-yxmkQNw1UgfpvEGlw","4":"https:\/\/www.youtube.com\/channel\/UCENUZbRr1cWOJEn2snygrfg","5":"https:\/\/www.youtube.com\/channel\/UCTLvXWIDDkEmX1MhSZPi1MQ","6":"https:\/\/www.youtube.com\/channel\/UCZVeE4pxO9AqvGh74KYg2ig","7":"https:\/\/www.youtube.com\/channel\/UC8zl8cNK71tTS6HAdHZynZQ","8":"https:\/\/www.youtube.com\/c\/PrettyPastelPlease","9":"https:\/\/www.youtube.com\/channel\/UCH3y9O7pO-YYfU4bbcG45IA","10":"https:\/\/www.youtube.com\/channel\/UCWbq9_8fq3FqideQ3kQ47hw","11":"https:\/\/www.youtube.com\/channel\/UC88YYy0Bsk9VrVRKhklnNBg","12":"https:\/\/www.youtube.com\/channel\/UCvU3Lrgb4cPOsC3iyqEVu-Q","13":"https:\/\/www.youtube.com\/channel\/UCDaIWaaiOOmTWC9XEEigLtA","14":"https:\/\/www.youtube.com\/c\/pastel_imAhottie","15":"https:\/\/www.youtube.com\/channel\/UCNaqXQLhcLUjfc9eSxh0DPw","16":"https:\/\/www.youtube.com\/c\/PastelPlotterSonoriza%C3%A7%C3%A3oeFilmagem","17":"https:\/\/www.youtube.com\/channel\/UCFnUyWqZ2kJ3MoaxXgQt5Cw","18":"https:\/\/www.youtube.com\/channel\/UCgbHSW3RTCHYDZ6mJweu1XA","19":"https:\/\/www.youtube.com\/c\/HelloPastelBlossomTV"},"1":{"0":"https:\/\/www.youtube.com\/c\/WildPastelHair","1":"https:\/\/www.youtube.com\/c\/AlessandraSantosPastel","2":"https:\/\/www.youtube.com\/channel\/UCSF6vx__8xdAnUIA_fcmB2Q","3":"https:\/\/www.youtube.com\/channel\/UCIjMZ-yxmkQNw1UgfpvEGlw","4":"https:\/\/www.youtube.com\/channel\/UCENUZbRr1cWOJEn2snygrfg","5":"https:\/\/www.youtube.com\/channel\/UCTLvXWIDDkEmX1MhSZPi1MQ","6":"https:\/\/www.youtube.com\/channel\/UCZVeE4pxO9AqvGh74KYg2ig","7":"https:\/\/www.youtube.com\/channel\/UC8zl8cNK71tTS6HAdHZynZQ","8":"https:\/\/www.youtube.com\/c\/PrettyPastelPlease","9":"https:\/\/www.youtube.com\/channel\/UCH3y9O7pO-YYfU4bbcG45IA","10":"https:\/\/www.youtube.com\/channel\/UCWbq9_8fq3FqideQ3kQ47hw","11":"https:\/\/www.youtube.com\/channel\/UC88YYy0Bsk9VrVRKhklnNBg","12":"https:\/\/www.youtube.com\/channel\/UCvU3Lrgb4cPOsC3iyqEVu-Q","13":"https:\/\/www.youtube.com\/channel\/UCDaIWaaiOOmTWC9XEEigLtA","14":"https:\/\/www.youtube.com\/c\/pastel_imAhottie","15":"https:\/\/www.youtube.com\/channel\/UCNaqXQLhcLUjfc9eSxh0DPw","16":"https:\/\/www.youtube.com\/c\/PastelPlotterSonoriza%C3%A7%C3%A3oeFilmagem","17":"https:\/\/www.youtube.com\/channel\/UCFnUyWqZ2kJ3MoaxXgQt5Cw","18":"https:\/\/www.youtube.com\/channel\/UCgbHSW3RTCHYDZ6mJweu1XA","19":"https:\/\/www.youtube.com\/c\/HelloPastelBlossomTV"},"2":{"0":"https:\/\/www.youtube.com\/c\/WildPastelHair","1":"https:\/\/www.youtube.com\/c\/AlessandraSantosPastel","2":"https:\/\/www.youtube.com\/channel\/UCSF6vx__8xdAnUIA_fcmB2Q","3":"https:\/\/www.youtube.com\/channel\/UCIjMZ-yxmkQNw1UgfpvEGlw","4":"https:\/\/www.youtube.com\/channel\/UCENUZbRr1cWOJEn2snygrfg","5":"https:\/\/www.youtube.com\/channel\/UCTLvXWIDDkEmX1MhSZPi1MQ","6":"https:\/\/www.youtube.com\/channel\/UCZVeE4pxO9AqvGh74KYg2ig","7":"https:\/\/www.youtube.com\/channel\/UC8zl8cNK71tTS6HAdHZynZQ","8":"https:\/\/www.youtube.com\/c\/PrettyPastelPlease","9":"https:\/\/www.youtube.com\/channel\/UCH3y9O7pO-YYfU4bbcG45IA","10":"https:\/\/www.youtube.com\/channel\/UCWbq9_8fq3FqideQ3kQ47hw","11":"https:\/\/www.youtube.com\/channel\/UC88YYy0Bsk9VrVRKhklnNBg","12":"https:\/\/www.youtube.com\/channel\/UCvU3Lrgb4cPOsC3iyqEVu-Q","13":"https:\/\/www.youtube.com\/channel\/UCDaIWaaiOOmTWC9XEEigLtA","14":"https:\/\/www.youtube.com\/c\/pastel_imAhottie","15":"https:\/\/www.youtube.com\/channel\/UCNaqXQLhcLUjfc9eSxh0DPw","16":"https:\/\/www.youtube.com\/c\/PastelPlotterSonoriza%C3%A7%C3%A3oeFilmagem","17":"https:\/\/www.youtube.com\/channel\/UCFnUyWqZ2kJ3MoaxXgQt5Cw","18":"https:\/\/www.youtube.com\/channel\/UCgbHSW3RTCHYDZ6mJweu1XA","19":"https:\/\/www.youtube.com\/c\/HelloPastelBlossomTV"},"3":{"0":"https:\/\/www.youtube.com\/c\/WildPastelHair","1":"https:\/\/www.youtube.com\/c\/AlessandraSantosPastel","2":"https:\/\/www.youtube.com\/channel\/UCSF6vx__8xdAnUIA_fcmB2Q","3":"https:\/\/www.youtube.com\/channel\/UCIjMZ-yxmkQNw1UgfpvEGlw","4":"https:\/\/www.youtube.com\/channel\/UCENUZbRr1cWOJEn2snygrfg","5":"https:\/\/www.youtube.com\/channel\/UCTLvXWIDDkEmX1MhSZPi1MQ","6":"https:\/\/www.youtube.com\/channel\/UCZVeE4pxO9AqvGh74KYg2ig","7":"https:\/\/www.youtube.com\/channel\/UC8zl8cNK71tTS6HAdHZynZQ","8":"https:\/\/www.youtube.com\/c\/PrettyPastelPlease","9":"https:\/\/www.youtube.com\/channel\/UCH3y9O7pO-YYfU4bbcG45IA","10":"https:\/\/www.youtube.com\/channel\/UCWbq9_8fq3FqideQ3kQ47hw","11":"https:\/\/www.youtube.com\/channel\/UC88YYy0Bsk9VrVRKhklnNBg","12":"https:\/\/www.youtube.com\/channel\/UCvU3Lrgb4cPOsC3iyqEVu-Q","13":"https:\/\/www.youtube.com\/channel\/UCDaIWaaiOOmTWC9XEEigLtA","14":"https:\/\/www.youtube.com\/c\/pastel_imAhottie","15":"https:\/\/www.youtube.com\/channel\/UCNaqXQLhcLUjfc9eSxh0DPw","16":"https:\/\/www.youtube.com\/c\/PastelPlotterSonoriza%C3%A7%C3%A3oeFilmagem","17":"https:\/\/www.youtube.com\/channel\/UCFnUyWqZ2kJ3MoaxXgQt5Cw","18":"https:\/\/www.youtube.com\/channel\/UCgbHSW3RTCHYDZ6mJweu1XA","19":"https:\/\/www.youtube.com\/c\/HelloPastelBlossomTV"},"4":{"0":"https:\/\/www.youtube.com\/c\/WildPastelHair","1":"https:\/\/www.youtube.com\/c\/AlessandraSantosPastel","2":"https:\/\/www.youtube.com\/channel\/UCSF6vx__8xdAnUIA_fcmB2Q","3":"https:\/\/www.youtube.com\/channel\/UCIjMZ-yxmkQNw1UgfpvEGlw","4":"https:\/\/www.youtube.com\/channel\/UCENUZbRr1cWOJEn2snygrfg","5":"https:\/\/www.youtube.com\/channel\/UCTLvXWIDDkEmX1MhSZPi1MQ","6":"https:\/\/www.youtube.com\/channel\/UCZVeE4pxO9AqvGh74KYg2ig","7":"https:\/\/www.youtube.com\/channel\/UC8zl8cNK71tTS6HAdHZynZQ","8":"https:\/\/www.youtube.com\/c\/PrettyPastelPlease","9":"https:\/\/www.youtube.com\/channel\/UCH3y9O7pO-YYfU4bbcG45IA","10":"https:\/\/www.youtube.com\/channel\/UCWbq9_8fq3FqideQ3kQ47hw","11":"https:\/\/www.youtube.com\/channel\/UC88YYy0Bsk9VrVRKhklnNBg","12":"https:\/\/www.youtube.com\/channel\/UCvU3Lrgb4cPOsC3iyqEVu-Q","13":"https:\/\/www.youtube.com\/channel\/UCDaIWaaiOOmTWC9XEEigLtA","14":"https:\/\/www.youtube.com\/c\/pastel_imAhottie","15":"https:\/\/www.youtube.com\/channel\/UCNaqXQLhcLUjfc9eSxh0DPw","16":"https:\/\/www.youtube.com\/c\/PastelPlotterSonoriza%C3%A7%C3%A3oeFilmagem","17":"https:\/\/www.youtube.com\/channel\/UCFnUyWqZ2kJ3MoaxXgQt5Cw","18":"https:\/\/www.youtube.com\/channel\/UCgbHSW3RTCHYDZ6mJweu1XA","19":"https:\/\/www.youtube.com\/c\/HelloPastelBlossomTV"},"5":{"0":"https:\/\/www.youtube.com\/c\/WildPastelHair","1":"https:\/\/www.youtube.com\/c\/AlessandraSantosPastel","2":"https:\/\/www.youtube.com\/channel\/UCSF6vx__8xdAnUIA_fcmB2Q","3":"https:\/\/www.youtube.com\/channel\/UCIjMZ-yxmkQNw1UgfpvEGlw","4":"https:\/\/www.youtube.com\/channel\/UCENUZbRr1cWOJEn2snygrfg","5":"https:\/\/www.youtube.com\/channel\/UCTLvXWIDDkEmX1MhSZPi1MQ","6":"https:\/\/www.youtube.com\/channel\/UCZVeE4pxO9AqvGh74KYg2ig","7":"https:\/\/www.youtube.com\/channel\/UC8zl8cNK71tTS6HAdHZynZQ","8":"https:\/\/www.youtube.com\/c\/PrettyPastelPlease","9":"https:\/\/www.youtube.com\/channel\/UCH3y9O7pO-YYfU4bbcG45IA","10":"https:\/\/www.youtube.com\/channel\/UCWbq9_8fq3FqideQ3kQ47hw","11":"https:\/\/www.youtube.com\/channel\/UC88YYy0Bsk9VrVRKhklnNBg","12":"https:\/\/www.youtube.com\/channel\/UCvU3Lrgb4cPOsC3iyqEVu-Q","13":"https:\/\/www.youtube.com\/channel\/UCDaIWaaiOOmTWC9XEEigLtA","14":"https:\/\/www.youtube.com\/c\/pastel_imAhottie","15":"https:\/\/www.youtube.com\/channel\/UCNaqXQLhcLUjfc9eSxh0DPw","16":"https:\/\/www.youtube.com\/c\/PastelPlotterSonoriza%C3%A7%C3%A3oeFilmagem","17":"https:\/\/www.youtube.com\/channel\/UCFnUyWqZ2kJ3MoaxXgQt5Cw","18":"https:\/\/www.youtube.com\/channel\/UCgbHSW3RTCHYDZ6mJweu1XA","19":"https:\/\/www.youtube.com\/c\/HelloPastelBlossomTV"},"6":{"0":"https:\/\/www.youtube.com\/c\/WildPastelHair","1":"https:\/\/www.youtube.com\/c\/AlessandraSantosPastel","2":"https:\/\/www.youtube.com\/channel\/UCSF6vx__8xdAnUIA_fcmB2Q","3":"https:\/\/www.youtube.com\/channel\/UCIjMZ-yxmkQNw1UgfpvEGlw","4":"https:\/\/www.youtube.com\/channel\/UCENUZbRr1cWOJEn2snygrfg","5":"https:\/\/www.youtube.com\/channel\/UCTLvXWIDDkEmX1MhSZPi1MQ","6":"https:\/\/www.youtube.com\/channel\/UCZVeE4pxO9AqvGh74KYg2ig","7":"https:\/\/www.youtube.com\/channel\/UC8zl8cNK71tTS6HAdHZynZQ","8":"https:\/\/www.youtube.com\/c\/PrettyPastelPlease","9":"https:\/\/www.youtube.com\/channel\/UCH3y9O7pO-YYfU4bbcG45IA","10":"https:\/\/www.youtube.com\/channel\/UCWbq9_8fq3FqideQ3kQ47hw","11":"https:\/\/www.youtube.com\/channel\/UC88YYy0Bsk9VrVRKhklnNBg","12":"https:\/\/www.youtube.com\/channel\/UCvU3Lrgb4cPOsC3iyqEVu-Q","13":"https:\/\/www.youtube.com\/channel\/UCDaIWaaiOOmTWC9XEEigLtA","14":"https:\/\/www.youtube.com\/c\/pastel_imAhottie","15":"https:\/\/www.youtube.com\/channel\/UCNaqXQLhcLUjfc9eSxh0DPw","16":"https:\/\/www.youtube.com\/c\/PastelPlotterSonoriza%C3%A7%C3%A3oeFilmagem","17":"https:\/\/www.youtube.com\/channel\/UCFnUyWqZ2kJ3MoaxXgQt5Cw","18":"https:\/\/www.youtube.com\/channel\/UCgbHSW3RTCHYDZ6mJweu1XA","19":"https:\/\/www.youtube.com\/c\/HelloPastelBlossomTV"},"7":{"0":"https:\/\/www.youtube.com\/c\/WildPastelHair","1":"https:\/\/www.youtube.com\/c\/AlessandraSantosPastel","2":"https:\/\/www.youtube.com\/channel\/UCSF6vx__8xdAnUIA_fcmB2Q","3":"https:\/\/www.youtube.com\/channel\/UCIjMZ-yxmkQNw1UgfpvEGlw","4":"https:\/\/www.youtube.com\/channel\/UCENUZbRr1cWOJEn2snygrfg","5":"https:\/\/www.youtube.com\/channel\/UCTLvXWIDDkEmX1MhSZPi1MQ","6":"https:\/\/www.youtube.com\/channel\/UCZVeE4pxO9AqvGh74KYg2ig","7":"https:\/\/www.youtube.com\/channel\/UC8zl8cNK71tTS6HAdHZynZQ","8":"https:\/\/www.youtube.com\/c\/PrettyPastelPlease","9":"https:\/\/www.youtube.com\/channel\/UCH3y9O7pO-YYfU4bbcG45IA","10":"https:\/\/www.youtube.com\/channel\/UCWbq9_8fq3FqideQ3kQ47hw","11":"https:\/\/www.youtube.com\/channel\/UC88YYy0Bsk9VrVRKhklnNBg","12":"https:\/\/www.youtube.com\/channel\/UCvU3Lrgb4cPOsC3iyqEVu-Q","13":"https:\/\/www.youtube.com\/channel\/UCDaIWaaiOOmTWC9XEEigLtA","14":"https:\/\/www.youtube.com\/c\/pastel_imAhottie","15":"https:\/\/www.youtube.com\/channel\/UCNaqXQLhcLUjfc9eSxh0DPw","16":"https:\/\/www.youtube.com\/c\/PastelPlotterSonoriza%C3%A7%C3%A3oeFilmagem","17":"https:\/\/www.youtube.com\/channel\/UCFnUyWqZ2kJ3MoaxXgQt5Cw","18":"https:\/\/www.youtube.com\/channel\/UCgbHSW3RTCHYDZ6mJweu1XA","19":"https:\/\/www.youtube.com\/c\/HelloPastelBlossomTV"},"8":{"0":"https:\/\/www.youtube.com\/c\/WildPastelHair","1":"https:\/\/www.youtube.com\/c\/AlessandraSantosPastel","2":"https:\/\/www.youtube.com\/channel\/UCSF6vx__8xdAnUIA_fcmB2Q","3":"https:\/\/www.youtube.com\/channel\/UCIjMZ-yxmkQNw1UgfpvEGlw","4":"https:\/\/www.youtube.com\/channel\/UCENUZbRr1cWOJEn2snygrfg","5":"https:\/\/www.youtube.com\/channel\/UCTLvXWIDDkEmX1MhSZPi1MQ","6":"https:\/\/www.youtube.com\/channel\/UCZVeE4pxO9AqvGh74KYg2ig","7":"https:\/\/www.youtube.com\/channel\/UC8zl8cNK71tTS6HAdHZynZQ","8":"https:\/\/www.youtube.com\/c\/PrettyPastelPlease","9":"https:\/\/www.youtube.com\/channel\/UCH3y9O7pO-YYfU4bbcG45IA","10":"https:\/\/www.youtube.com\/channel\/UCWbq9_8fq3FqideQ3kQ47hw","11":"https:\/\/www.youtube.com\/channel\/UC88YYy0Bsk9VrVRKhklnNBg","12":"https:\/\/www.youtube.com\/channel\/UCvU3Lrgb4cPOsC3iyqEVu-Q","13":"https:\/\/www.youtube.com\/channel\/UCDaIWaaiOOmTWC9XEEigLtA","14":"https:\/\/www.youtube.com\/c\/pastel_imAhottie","15":"https:\/\/www.youtube.com\/channel\/UCNaqXQLhcLUjfc9eSxh0DPw","16":"https:\/\/www.youtube.com\/c\/PastelPlotterSonoriza%C3%A7%C3%A3oeFilmagem","17":"https:\/\/www.youtube.com\/channel\/UCFnUyWqZ2kJ3MoaxXgQt5Cw","18":"https:\/\/www.youtube.com\/channel\/UCgbHSW3RTCHYDZ6mJweu1XA","19":"https:\/\/www.youtube.com\/c\/HelloPastelBlossomTV"},"9":{"0":"https:\/\/www.youtube.com\/c\/WildPastelHair","1":"https:\/\/www.youtube.com\/c\/AlessandraSantosPastel","2":"https:\/\/www.youtube.com\/channel\/UCSF6vx__8xdAnUIA_fcmB2Q","3":"https:\/\/www.youtube.com\/channel\/UCIjMZ-yxmkQNw1UgfpvEGlw","4":"https:\/\/www.youtube.com\/channel\/UCENUZbRr1cWOJEn2snygrfg","5":"https:\/\/www.youtube.com\/channel\/UCTLvXWIDDkEmX1MhSZPi1MQ","6":"https:\/\/www.youtube.com\/channel\/UCZVeE4pxO9AqvGh74KYg2ig","7":"https:\/\/www.youtube.com\/channel\/UC8zl8cNK71tTS6HAdHZynZQ","8":"https:\/\/www.youtube.com\/c\/PrettyPastelPlease","9":"https:\/\/www.youtube.com\/channel\/UCH3y9O7pO-YYfU4bbcG45IA","10":"https:\/\/www.youtube.com\/channel\/UCWbq9_8fq3FqideQ3kQ47hw","11":"https:\/\/www.youtube.com\/channel\/UC88YYy0Bsk9VrVRKhklnNBg","12":"https:\/\/www.youtube.com\/channel\/UCvU3Lrgb4cPOsC3iyqEVu-Q","13":"https:\/\/www.youtube.com\/channel\/UCDaIWaaiOOmTWC9XEEigLtA","14":"https:\/\/www.youtube.com\/c\/pastel_imAhottie","15":"https:\/\/www.youtube.com\/channel\/UCNaqXQLhcLUjfc9eSxh0DPw","16":"https:\/\/www.youtube.com\/c\/PastelPlotterSonoriza%C3%A7%C3%A3oeFilmagem","17":"https:\/\/www.youtube.com\/channel\/UCFnUyWqZ2kJ3MoaxXgQt5Cw","18":"https:\/\/www.youtube.com\/channel\/UCgbHSW3RTCHYDZ6mJweu1XA","19":"https:\/\/www.youtube.com\/c\/HelloPastelBlossomTV"},"10":{"0":"https:\/\/www.youtube.com\/c\/WildPastelHair","1":"https:\/\/www.youtube.com\/c\/AlessandraSantosPastel","2":"https:\/\/www.youtube.com\/channel\/UCSF6vx__8xdAnUIA_fcmB2Q","3":"https:\/\/www.youtube.com\/channel\/UCIjMZ-yxmkQNw1UgfpvEGlw","4":"https:\/\/www.youtube.com\/channel\/UCENUZbRr1cWOJEn2snygrfg","5":"https:\/\/www.youtube.com\/channel\/UCTLvXWIDDkEmX1MhSZPi1MQ","6":"https:\/\/www.youtube.com\/channel\/UCZVeE4pxO9AqvGh74KYg2ig","7":"https:\/\/www.youtube.com\/channel\/UC8zl8cNK71tTS6HAdHZynZQ","8":"https:\/\/www.youtube.com\/c\/PrettyPastelPlease","9":"https:\/\/www.youtube.com\/channel\/UCH3y9O7pO-YYfU4bbcG45IA","10":"https:\/\/www.youtube.com\/channel\/UCWbq9_8fq3FqideQ3kQ47hw","11":"https:\/\/www.youtube.com\/channel\/UC88YYy0Bsk9VrVRKhklnNBg","12":"https:\/\/www.youtube.com\/channel\/UCvU3Lrgb4cPOsC3iyqEVu-Q","13":"https:\/\/www.youtube.com\/channel\/UCDaIWaaiOOmTWC9XEEigLtA","14":"https:\/\/www.youtube.com\/c\/pastel_imAhottie","15":"https:\/\/www.youtube.com\/channel\/UCNaqXQLhcLUjfc9eSxh0DPw","16":"https:\/\/www.youtube.com\/c\/PastelPlotterSonoriza%C3%A7%C3%A3oeFilmagem","17":"https:\/\/www.youtube.com\/channel\/UCFnUyWqZ2kJ3MoaxXgQt5Cw","18":"https:\/\/www.youtube.com\/channel\/UCgbHSW3RTCHYDZ6mJweu1XA","19":"https:\/\/www.youtube.com\/c\/HelloPastelBlossomTV"},"11":{"0":"https:\/\/www.youtube.com\/c\/WildPastelHair","1":"https:\/\/www.youtube.com\/c\/AlessandraSantosPastel","2":"https:\/\/www.youtube.com\/channel\/UCSF6vx__8xdAnUIA_fcmB2Q","3":"https:\/\/www.youtube.com\/channel\/UCIjMZ-yxmkQNw1UgfpvEGlw","4":"https:\/\/www.youtube.com\/channel\/UCENUZbRr1cWOJEn2snygrfg","5":"https:\/\/www.youtube.com\/channel\/UCTLvXWIDDkEmX1MhSZPi1MQ","6":"https:\/\/www.youtube.com\/channel\/UCZVeE4pxO9AqvGh74KYg2ig","7":"https:\/\/www.youtube.com\/channel\/UC8zl8cNK71tTS6HAdHZynZQ","8":"https:\/\/www.youtube.com\/c\/PrettyPastelPlease","9":"https:\/\/www.youtube.com\/channel\/UCH3y9O7pO-YYfU4bbcG45IA","10":"https:\/\/www.youtube.com\/channel\/UCWbq9_8fq3FqideQ3kQ47hw","11":"https:\/\/www.youtube.com\/channel\/UC88YYy0Bsk9VrVRKhklnNBg","12":"https:\/\/www.youtube.com\/channel\/UCvU3Lrgb4cPOsC3iyqEVu-Q","13":"https:\/\/www.youtube.com\/channel\/UCDaIWaaiOOmTWC9XEEigLtA","14":"https:\/\/www.youtube.com\/c\/pastel_imAhottie","15":"https:\/\/www.youtube.com\/channel\/UCNaqXQLhcLUjfc9eSxh0DPw","16":"https:\/\/www.youtube.com\/c\/PastelPlotterSonoriza%C3%A7%C3%A3oeFilmagem","17":"https:\/\/www.youtube.com\/channel\/UCFnUyWqZ2kJ3MoaxXgQt5Cw","18":"https:\/\/www.youtube.com\/channel\/UCgbHSW3RTCHYDZ6mJweu1XA","19":"https:\/\/www.youtube.com\/c\/HelloPastelBlossomTV"},"12":{"0":"https:\/\/www.youtube.com\/c\/WildPastelHair","1":"https:\/\/www.youtube.com\/c\/AlessandraSantosPastel","2":"https:\/\/www.youtube.com\/channel\/UCSF6vx__8xdAnUIA_fcmB2Q","3":"https:\/\/www.youtube.com\/channel\/UCIjMZ-yxmkQNw1UgfpvEGlw","4":"https:\/\/www.youtube.com\/channel\/UCENUZbRr1cWOJEn2snygrfg","5":"https:\/\/www.youtube.com\/channel\/UCTLvXWIDDkEmX1MhSZPi1MQ","6":"https:\/\/www.youtube.com\/channel\/UCZVeE4pxO9AqvGh74KYg2ig","7":"https:\/\/www.youtube.com\/channel\/UC8zl8cNK71tTS6HAdHZynZQ","8":"https:\/\/www.youtube.com\/c\/PrettyPastelPlease","9":"https:\/\/www.youtube.com\/channel\/UCH3y9O7pO-YYfU4bbcG45IA","10":"https:\/\/www.youtube.com\/channel\/UCWbq9_8fq3FqideQ3kQ47hw","11":"https:\/\/www.youtube.com\/channel\/UC88YYy0Bsk9VrVRKhklnNBg","12":"https:\/\/www.youtube.com\/channel\/UCvU3Lrgb4cPOsC3iyqEVu-Q","13":"https:\/\/www.youtube.com\/channel\/UCDaIWaaiOOmTWC9XEEigLtA","14":"https:\/\/www.youtube.com\/c\/pastel_imAhottie","15":"https:\/\/www.youtube.com\/channel\/UCNaqXQLhcLUjfc9eSxh0DPw","16":"https:\/\/www.youtube.com\/c\/PastelPlotterSonoriza%C3%A7%C3%A3oeFilmagem","17":"https:\/\/www.youtube.com\/channel\/UCFnUyWqZ2kJ3MoaxXgQt5Cw","18":"https:\/\/www.youtube.com\/channel\/UCgbHSW3RTCHYDZ6mJweu1XA","19":"https:\/\/www.youtube.com\/c\/HelloPastelBlossomTV"},"13":{"0":"https:\/\/www.youtube.com\/c\/WildPastelHair","1":"https:\/\/www.youtube.com\/c\/AlessandraSantosPastel","2":"https:\/\/www.youtube.com\/channel\/UCSF6vx__8xdAnUIA_fcmB2Q","3":"https:\/\/www.youtube.com\/channel\/UCIjMZ-yxmkQNw1UgfpvEGlw","4":"https:\/\/www.youtube.com\/channel\/UCENUZbRr1cWOJEn2snygrfg","5":"https:\/\/www.youtube.com\/channel\/UCTLvXWIDDkEmX1MhSZPi1MQ","6":"https:\/\/www.youtube.com\/channel\/UCZVeE4pxO9AqvGh74KYg2ig","7":"https:\/\/www.youtube.com\/channel\/UC8zl8cNK71tTS6HAdHZynZQ","8":"https:\/\/www.youtube.com\/c\/PrettyPastelPlease","9":"https:\/\/www.youtube.com\/channel\/UCH3y9O7pO-YYfU4bbcG45IA","10":"https:\/\/www.youtube.com\/channel\/UCWbq9_8fq3FqideQ3kQ47hw","11":"https:\/\/www.youtube.com\/channel\/UC88YYy0Bsk9VrVRKhklnNBg","12":"https:\/\/www.youtube.com\/channel\/UCvU3Lrgb4cPOsC3iyqEVu-Q","13":"https:\/\/www.youtube.com\/channel\/UCDaIWaaiOOmTWC9XEEigLtA","14":"https:\/\/www.youtube.com\/c\/pastel_imAhottie","15":"https:\/\/www.youtube.com\/channel\/UCNaqXQLhcLUjfc9eSxh0DPw","16":"https:\/\/www.youtube.com\/c\/PastelPlotterSonoriza%C3%A7%C3%A3oeFilmagem","17":"https:\/\/www.youtube.com\/channel\/UCFnUyWqZ2kJ3MoaxXgQt5Cw","18":"https:\/\/www.youtube.com\/channel\/UCgbHSW3RTCHYDZ6mJweu1XA","19":"https:\/\/www.youtube.com\/c\/HelloPastelBlossomTV"},"14":{"0":"https:\/\/www.youtube.com\/c\/WildPastelHair","1":"https:\/\/www.youtube.com\/c\/AlessandraSantosPastel","2":"https:\/\/www.youtube.com\/channel\/UCSF6vx__8xdAnUIA_fcmB2Q","3":"https:\/\/www.youtube.com\/channel\/UCIjMZ-yxmkQNw1UgfpvEGlw","4":"https:\/\/www.youtube.com\/channel\/UCENUZbRr1cWOJEn2snygrfg","5":"https:\/\/www.youtube.com\/channel\/UCTLvXWIDDkEmX1MhSZPi1MQ","6":"https:\/\/www.youtube.com\/channel\/UCZVeE4pxO9AqvGh74KYg2ig","7":"https:\/\/www.youtube.com\/channel\/UC8zl8cNK71tTS6HAdHZynZQ","8":"https:\/\/www.youtube.com\/c\/PrettyPastelPlease","9":"https:\/\/www.youtube.com\/channel\/UCH3y9O7pO-YYfU4bbcG45IA","10":"https:\/\/www.youtube.com\/channel\/UCWbq9_8fq3FqideQ3kQ47hw","11":"https:\/\/www.youtube.com\/channel\/UC88YYy0Bsk9VrVRKhklnNBg","12":"https:\/\/www.youtube.com\/channel\/UCvU3Lrgb4cPOsC3iyqEVu-Q","13":"https:\/\/www.youtube.com\/channel\/UCDaIWaaiOOmTWC9XEEigLtA","14":"https:\/\/www.youtube.com\/c\/pastel_imAhottie","15":"https:\/\/www.youtube.com\/channel\/UCNaqXQLhcLUjfc9eSxh0DPw","16":"https:\/\/www.youtube.com\/c\/PastelPlotterSonoriza%C3%A7%C3%A3oeFilmagem","17":"https:\/\/www.youtube.com\/channel\/UCFnUyWqZ2kJ3MoaxXgQt5Cw","18":"https:\/\/www.youtube.com\/channel\/UCgbHSW3RTCHYDZ6mJweu1XA","19":"https:\/\/www.youtube.com\/c\/HelloPastelBlossomTV"},"15":{"0":"https:\/\/www.youtube.com\/c\/WildPastelHair","1":"https:\/\/www.youtube.com\/c\/AlessandraSantosPastel","2":"https:\/\/www.youtube.com\/channel\/UCSF6vx__8xdAnUIA_fcmB2Q","3":"https:\/\/www.youtube.com\/channel\/UCIjMZ-yxmkQNw1UgfpvEGlw","4":"https:\/\/www.youtube.com\/channel\/UCENUZbRr1cWOJEn2snygrfg","5":"https:\/\/www.youtube.com\/channel\/UCTLvXWIDDkEmX1MhSZPi1MQ","6":"https:\/\/www.youtube.com\/channel\/UCZVeE4pxO9AqvGh74KYg2ig","7":"https:\/\/www.youtube.com\/channel\/UC8zl8cNK71tTS6HAdHZynZQ","8":"https:\/\/www.youtube.com\/c\/PrettyPastelPlease","9":"https:\/\/www.youtube.com\/channel\/UCH3y9O7pO-YYfU4bbcG45IA","10":"https:\/\/www.youtube.com\/channel\/UCWbq9_8fq3FqideQ3kQ47hw","11":"https:\/\/www.youtube.com\/channel\/UC88YYy0Bsk9VrVRKhklnNBg","12":"https:\/\/www.youtube.com\/channel\/UCvU3Lrgb4cPOsC3iyqEVu-Q","13":"https:\/\/www.youtube.com\/channel\/UCDaIWaaiOOmTWC9XEEigLtA","14":"https:\/\/www.youtube.com\/c\/pastel_imAhottie","15":"https:\/\/www.youtube.com\/channel\/UCNaqXQLhcLUjfc9eSxh0DPw","16":"https:\/\/www.youtube.com\/c\/PastelPlotterSonoriza%C3%A7%C3%A3oeFilmagem","17":"https:\/\/www.youtube.com\/channel\/UCFnUyWqZ2kJ3MoaxXgQt5Cw","18":"https:\/\/www.youtube.com\/channel\/UCgbHSW3RTCHYDZ6mJweu1XA","19":"https:\/\/www.youtube.com\/c\/HelloPastelBlossomTV"},"16":{"0":"https:\/\/www.youtube.com\/c\/WildPastelHair","1":"https:\/\/www.youtube.com\/c\/AlessandraSantosPastel","2":"https:\/\/www.youtube.com\/channel\/UCSF6vx__8xdAnUIA_fcmB2Q","3":"https:\/\/www.youtube.com\/channel\/UCIjMZ-yxmkQNw1UgfpvEGlw","4":"https:\/\/www.youtube.com\/channel\/UCENUZbRr1cWOJEn2snygrfg","5":"https:\/\/www.youtube.com\/channel\/UCTLvXWIDDkEmX1MhSZPi1MQ","6":"https:\/\/www.youtube.com\/channel\/UCZVeE4pxO9AqvGh74KYg2ig","7":"https:\/\/www.youtube.com\/channel\/UC8zl8cNK71tTS6HAdHZynZQ","8":"https:\/\/www.youtube.com\/c\/PrettyPastelPlease","9":"https:\/\/www.youtube.com\/channel\/UCH3y9O7pO-YYfU4bbcG45IA","10":"https:\/\/www.youtube.com\/channel\/UCWbq9_8fq3FqideQ3kQ47hw","11":"https:\/\/www.youtube.com\/channel\/UC88YYy0Bsk9VrVRKhklnNBg","12":"https:\/\/www.youtube.com\/channel\/UCvU3Lrgb4cPOsC3iyqEVu-Q","13":"https:\/\/www.youtube.com\/channel\/UCDaIWaaiOOmTWC9XEEigLtA","14":"https:\/\/www.youtube.com\/c\/pastel_imAhottie","15":"https:\/\/www.youtube.com\/channel\/UCNaqXQLhcLUjfc9eSxh0DPw","16":"https:\/\/www.youtube.com\/c\/PastelPlotterSonoriza%C3%A7%C3%A3oeFilmagem","17":"https:\/\/www.youtube.com\/channel\/UCFnUyWqZ2kJ3MoaxXgQt5Cw","18":"https:\/\/www.youtube.com\/channel\/UCgbHSW3RTCHYDZ6mJweu1XA","19":"https:\/\/www.youtube.com\/c\/HelloPastelBlossomTV"},"17":{"0":"https:\/\/www.youtube.com\/c\/WildPastelHair","1":"https:\/\/www.youtube.com\/c\/AlessandraSantosPastel","2":"https:\/\/www.youtube.com\/channel\/UCSF6vx__8xdAnUIA_fcmB2Q","3":"https:\/\/www.youtube.com\/channel\/UCIjMZ-yxmkQNw1UgfpvEGlw","4":"https:\/\/www.youtube.com\/channel\/UCENUZbRr1cWOJEn2snygrfg","5":"https:\/\/www.youtube.com\/channel\/UCTLvXWIDDkEmX1MhSZPi1MQ","6":"https:\/\/www.youtube.com\/channel\/UCZVeE4pxO9AqvGh74KYg2ig","7":"https:\/\/www.youtube.com\/channel\/UC8zl8cNK71tTS6HAdHZynZQ","8":"https:\/\/www.youtube.com\/c\/PrettyPastelPlease","9":"https:\/\/www.youtube.com\/channel\/UCH3y9O7pO-YYfU4bbcG45IA","10":"https:\/\/www.youtube.com\/channel\/UCWbq9_8fq3FqideQ3kQ47hw","11":"https:\/\/www.youtube.com\/channel\/UC88YYy0Bsk9VrVRKhklnNBg","12":"https:\/\/www.youtube.com\/channel\/UCvU3Lrgb4cPOsC3iyqEVu-Q","13":"https:\/\/www.youtube.com\/channel\/UCDaIWaaiOOmTWC9XEEigLtA","14":"https:\/\/www.youtube.com\/c\/pastel_imAhottie","15":"https:\/\/www.youtube.com\/channel\/UCNaqXQLhcLUjfc9eSxh0DPw","16":"https:\/\/www.youtube.com\/c\/PastelPlotterSonoriza%C3%A7%C3%A3oeFilmagem","17":"https:\/\/www.youtube.com\/channel\/UCFnUyWqZ2kJ3MoaxXgQt5Cw","18":"https:\/\/www.youtube.com\/channel\/UCgbHSW3RTCHYDZ6mJweu1XA","19":"https:\/\/www.youtube.com\/c\/HelloPastelBlossomTV"},"18":{"0":"https:\/\/www.youtube.com\/c\/WildPastelHair","1":"https:\/\/www.youtube.com\/c\/AlessandraSantosPastel","2":"https:\/\/www.youtube.com\/channel\/UCSF6vx__8xdAnUIA_fcmB2Q","3":"https:\/\/www.youtube.com\/channel\/UCIjMZ-yxmkQNw1UgfpvEGlw","4":"https:\/\/www.youtube.com\/channel\/UCENUZbRr1cWOJEn2snygrfg","5":"https:\/\/www.youtube.com\/channel\/UCTLvXWIDDkEmX1MhSZPi1MQ","6":"https:\/\/www.youtube.com\/channel\/UCZVeE4pxO9AqvGh74KYg2ig","7":"https:\/\/www.youtube.com\/channel\/UC8zl8cNK71tTS6HAdHZynZQ","8":"https:\/\/www.youtube.com\/c\/PrettyPastelPlease","9":"https:\/\/www.youtube.com\/channel\/UCH3y9O7pO-YYfU4bbcG45IA","10":"https:\/\/www.youtube.com\/channel\/UCWbq9_8fq3FqideQ3kQ47hw","11":"https:\/\/www.youtube.com\/channel\/UC88YYy0Bsk9VrVRKhklnNBg","12":"https:\/\/www.youtube.com\/channel\/UCvU3Lrgb4cPOsC3iyqEVu-Q","13":"https:\/\/www.youtube.com\/channel\/UCDaIWaaiOOmTWC9XEEigLtA","14":"https:\/\/www.youtube.com\/c\/pastel_imAhottie","15":"https:\/\/www.youtube.com\/channel\/UCNaqXQLhcLUjfc9eSxh0DPw","16":"https:\/\/www.youtube.com\/c\/PastelPlotterSonoriza%C3%A7%C3%A3oeFilmagem","17":"https:\/\/www.youtube.com\/channel\/UCFnUyWqZ2kJ3MoaxXgQt5Cw","18":"https:\/\/www.youtube.com\/channel\/UCgbHSW3RTCHYDZ6mJweu1XA","19":"https:\/\/www.youtube.com\/c\/HelloPastelBlossomTV"},"19":{"0":"https:\/\/www.youtube.com\/c\/WildPastelHair","1":"https:\/\/www.youtube.com\/c\/AlessandraSantosPastel","2":"https:\/\/www.youtube.com\/channel\/UCSF6vx__8xdAnUIA_fcmB2Q","3":"https:\/\/www.youtube.com\/channel\/UCIjMZ-yxmkQNw1UgfpvEGlw","4":"https:\/\/www.youtube.com\/channel\/UCENUZbRr1cWOJEn2snygrfg","5":"https:\/\/www.youtube.com\/channel\/UCTLvXWIDDkEmX1MhSZPi1MQ","6":"https:\/\/www.youtube.com\/channel\/UCZVeE4pxO9AqvGh74KYg2ig","7":"https:\/\/www.youtube.com\/channel\/UC8zl8cNK71tTS6HAdHZynZQ","8":"https:\/\/www.youtube.com\/c\/PrettyPastelPlease","9":"https:\/\/www.youtube.com\/channel\/UCH3y9O7pO-YYfU4bbcG45IA","10":"https:\/\/www.youtube.com\/channel\/UCWbq9_8fq3FqideQ3kQ47hw","11":"https:\/\/www.youtube.com\/channel\/UC88YYy0Bsk9VrVRKhklnNBg","12":"https:\/\/www.youtube.com\/channel\/UCvU3Lrgb4cPOsC3iyqEVu-Q","13":"https:\/\/www.youtube.com\/channel\/UCDaIWaaiOOmTWC9XEEigLtA","14":"https:\/\/www.youtube.com\/c\/pastel_imAhottie","15":"https:\/\/www.youtube.com\/channel\/UCNaqXQLhcLUjfc9eSxh0DPw","16":"https:\/\/www.youtube.com\/c\/PastelPlotterSonoriza%C3%A7%C3%A3oeFilmagem","17":"https:\/\/www.youtube.com\/channel\/UCFnUyWqZ2kJ3MoaxXgQt5Cw","18":"https:\/\/www.youtube.com\/channel\/UCgbHSW3RTCHYDZ6mJweu1XA","19":"https:\/\/www.youtube.com\/c\/HelloPastelBlossomTV"}},"Titles":{"0":"Become shorter","1":"get pale smooth soft skin","2":"better drawing subliminal","3":"nose subliminal","4":"grow longer hair subliminal","5":"become taller","6":"nana komatsu {request}","7":"get your desired body and face subliminal","8":"look like you want to subliminal","9":"change your past \u3010Thanksgiving Ver\u3011","10":"Crush subliminal \u3010 boys and girls \u3011","11":"yellow undertone","12":"eyes subliminal [reuploaded]","13":"anime girl subliminal {request}","14":"Learn korean","15":"kpop idol subliminal","16":"\uff4d\uff41\uff4c\uff49\uff42\uff55\uff53\u3000\uff4c\uff45\uff47\uff41\uff43\uff59\u3000\uff42\uff4f\uff4f\uff53\uff54\uff45\uff52( reupload )","17":"Ulzzang \u3010boys and girls\u3011","18":"combo #1","19":"go to any kpop concert\u3010Easter Ver \u3011"},"Video_URL":{"0":"https:\/\/www.youtube.com\/watch?v=jJ3tQ8m3BTQ","1":"https:\/\/www.youtube.com\/watch?v=PSQ-uymLduc","2":"https:\/\/www.youtube.com\/watch?v=3dI9KnuFTuU","3":"https:\/\/www.youtube.com\/watch?v=Tagr9N1yQOM","4":"https:\/\/www.youtube.com\/watch?v=ZN9cn9vcO0g","5":"https:\/\/www.youtube.com\/watch?v=fNnkET8SH1I","6":"https:\/\/www.youtube.com\/watch?v=Bd2qIwJ9yfs","7":"https:\/\/www.youtube.com\/watch?v=KhsIdroe9q8","8":"https:\/\/www.youtube.com\/watch?v=HQscI-5j8Fw","9":"https:\/\/www.youtube.com\/watch?v=yFY8NJOyts8","10":"https:\/\/www.youtube.com\/watch?v=neR-wb_9nFY","11":"https:\/\/www.youtube.com\/watch?v=R6a3LUJzQjw","12":"https:\/\/www.youtube.com\/watch?v=wJmmoJ7eCjU","13":"https:\/\/www.youtube.com\/watch?v=f1fiZ4WYHyQ","14":"https:\/\/www.youtube.com\/watch?v=0A6zCrV_QsY","15":"https:\/\/www.youtube.com\/watch?v=pZIsqCeFjCc","16":"https:\/\/www.youtube.com\/watch?v=1JIe-i3SOQs","17":"https:\/\/www.youtube.com\/watch?v=0N3gDmEqVXg","18":"https:\/\/www.youtube.com\/watch?v=RJOCZPZALQU","19":"https:\/\/www.youtube.com\/watch?v=u4rchF6ADR0"},"Date":{"0":"4 years ago","1":"4 years ago","2":"4 years ago","3":"4 years ago","4":"4 years ago","5":"4 years ago","6":"4 years ago","7":"4 years ago","8":"4 years ago","9":"4 years ago","10":"4 years ago","11":"4 years ago","12":"4 years ago","13":"4 years ago","14":"4 years ago","15":"4 years ago","16":"4 years ago","17":"4 years ago","18":"4 years ago","19":"4 years ago"},"View_2022-01-12":{"0":"2.1M views","1":"362K views","2":"257K views","3":"53K views","4":"19K views","5":"15K views","6":"15K views","7":"15K views","8":"10K views","9":"9.3K views","10":"9K views","11":"8.9K views","12":"8K views","13":"7.8K views","14":"6.9K views","15":"6.4K views","16":"5.6K views","17":"5.2K views","18":"4.4K views","19":"3.8K views"},"Subs_2022-01-12":{"0":"10.8K subscribers","1":"10.8K subscribers","2":"10.8K subscribers","3":"10.8K subscribers","4":"10.8K subscribers","5":"10.8K subscribers","6":"10.8K subscribers","7":"10.8K subscribers","8":"10.8K subscribers","9":"10.8K subscribers","10":"10.8K subscribers","11":"10.8K subscribers","12":"10.8K subscribers","13":"10.8K subscribers","14":"10.8K subscribers","15":"10.8K subscribers","16":"10.8K subscribers","17":"10.8K subscribers","18":"10.8K subscribers","19":"10.8K subscribers"}}