{"Category":{"0":"pastel","1":"pastel","2":"pastel","3":"pastel","4":"pastel","5":"pastel","6":"pastel","7":"pastel","8":"pastel","9":"pastel","10":"pastel","11":"pastel","12":"pastel","13":"pastel","14":"pastel","15":"pastel","16":"pastel","17":"pastel","18":"pastel","19":"pastel"},"Channel":{"0":"Pastel","1":"Alessandra Santos Pastel","2":"Pastel","3":"Aninha Santos Pastel","4":"Pastel _Sisters","5":"Curso Pastel de Feira","6":"Pastel Flurry","7":"Pastel Ice Eating ASMR","8":"Pretty Pastel Please","9":"\u2022 pastel clouds \u2022","10":"*Pastel Moonlight*","11":"Pastel Peryton","12":"Pastel","13":"Pastel","14":"\u2022 p a s t e l \u2022","15":"Pastel Sounds","16":"Pastel Plotter Sonoriza\u00e7\u00e3o e Filmagem","17":"Silvana Santos Pastel","18":"pastel em a\u00e7\u00e3o","19":"Hello Pastel Blossom TV"},"Inscritos":{"0":"382K subscribers","1":"1.21M subscribers","2":"1.69K subscribers","3":"3.37K subscribers","4":"81K subscribers","5":"7 subscribers","6":"440K subscribers","7":"9.62K subscribers","8":"717K subscribers","9":"238K subscribers","10":"99.2K subscribers","11":"69.8K subscribers","12":"61 subscribers","13":null,"14":"32K subscribers","15":"10.8K subscribers","16":"2.79K subscribers","17":"10.9K subscribers","18":"31 subscribers","19":"82.4K subscribers"},"Videos":{"0":"458 videos","1":"504 videos","2":"15 videos","3":"45 videos","4":"64 videos","5":"2 videos","6":"31 videos","7":"2,500 videos","8":"259 videos","9":"81 videos","10":"135 videos","11":"68 videos","12":"28 videos","13":"9 videos","14":"150 videos","15":"22 videos","16":"63 videos","17":"62 videos","18":"52 videos","19":"328 videos"},"Ch_URL":{"0":"https:\/\/www.youtube.com\/c\/WildPastelHair","1":"https:\/\/www.youtube.com\/c\/AlessandraSantosPastel","2":"https:\/\/www.youtube.com\/channel\/UCSF6vx__8xdAnUIA_fcmB2Q","3":"https:\/\/www.youtube.com\/channel\/UCIjMZ-yxmkQNw1UgfpvEGlw","4":"https:\/\/www.youtube.com\/channel\/UCENUZbRr1cWOJEn2snygrfg","5":"https:\/\/www.youtube.com\/channel\/UCTLvXWIDDkEmX1MhSZPi1MQ","6":"https:\/\/www.youtube.com\/channel\/UCZVeE4pxO9AqvGh74KYg2ig","7":"https:\/\/www.youtube.com\/channel\/UC8zl8cNK71tTS6HAdHZynZQ","8":"https:\/\/www.youtube.com\/c\/PrettyPastelPlease","9":"https:\/\/www.youtube.com\/channel\/UCH3y9O7pO-YYfU4bbcG45IA","10":"https:\/\/www.youtube.com\/channel\/UCWbq9_8fq3FqideQ3kQ47hw","11":"https:\/\/www.youtube.com\/channel\/UC88YYy0Bsk9VrVRKhklnNBg","12":"https:\/\/www.youtube.com\/channel\/UCvU3Lrgb4cPOsC3iyqEVu-Q","13":"https:\/\/www.youtube.com\/channel\/UCDaIWaaiOOmTWC9XEEigLtA","14":"https:\/\/www.youtube.com\/c\/pastel_imAhottie","15":"https:\/\/www.youtube.com\/channel\/UCNaqXQLhcLUjfc9eSxh0DPw","16":"https:\/\/www.youtube.com\/c\/PastelPlotterSonoriza%C3%A7%C3%A3oeFilmagem","17":"https:\/\/www.youtube.com\/channel\/UCFnUyWqZ2kJ3MoaxXgQt5Cw","18":"https:\/\/www.youtube.com\/channel\/UCgbHSW3RTCHYDZ6mJweu1XA","19":"https:\/\/www.youtube.com\/c\/HelloPastelBlossomTV"}}