{"Channel":{"0":"Claudia Avelar","1":"Claudia Avelar","2":"Claudia Avelar","3":"Claudia Avelar","4":"Claudia Avelar","5":"Claudia Avelar","6":"Claudia Avelar","7":"Claudia Avelar"},"Titles":{"0":"Boas-Vindas","1":"Passo a passo para montar seu planejamento financeiro pessoal","2":"Repetimos padr\u00f5es familiares nas finan\u00e7as?","3":"Como evitar imprevistos nas finan\u00e7as","4":"Passo a passo do meu Planejamento Financeiro","5":"Planejamento Financeiro ferramenta de realizar sonhos","6":"Tornando o Planejamento Financeiro divertido","7":"O seu sal\u00e1rio nunca sobra, mesmo cortando todos os gastos?"}}