{"Channel":{"0":"Finan\u00e7as com a Tia L\u00ea!","1":"Finan\u00e7as com a Tia L\u00ea!","2":"Finan\u00e7as com a Tia L\u00ea!","3":"Finan\u00e7as com a Tia L\u00ea!","4":"Finan\u00e7as com a Tia L\u00ea!","5":"Finan\u00e7as com a Tia L\u00ea!","6":"Finan\u00e7as com a Tia L\u00ea!"},"Titles":{"0":"COMO ENSINAR OS FILHOS A CUIDAR DO DINHEIRO - Por faixa et\u00e1ria!","1":"COMO COME\u00c7AR A ORGANIZAR AS FINAN\u00c7AS - Parte 1","2":"COMO MONTAR UM OR\u00c7AMENTO FAMILIAR - Com Intelig\u00eancia","3":"COMO COME\u00c7AR A ORGANIZAR AS FINAN\u00c7AS - Parte 2","4":"PARA QUE O DINHEIRO SERVE? - 4 principais fun\u00e7\u00f5es!","5":"IMPORT\u00c2NCIA DA EDUCA\u00c7\u00c3O FINANCEIRA - 3 formas de come\u00e7ar a educar seu filho!","6":"COMO ECONOMIZAR NAS COMPRAS DE NATAL - 7 Dicas Pr\u00e1ticas!"}}